{
  "name": "frontend",
  "version": "1.0.0",
  "build": "2026-01-13_14-38-49-097Z",
  "root": "ui",
  "dir": "deploy/build",
  "output": "deploy/output/frontend",
  "venv": false,
  "requires": [],
  "script": "build.ts",
  "targets": [
    {
      "glob_source": "../ui/Oracle/src-tauri/target/release/Oracle.exe",
      "output": "Oracle.exe",
      "release_only": true
    },
    {
      "glob_source": "../README.md",
      "output": "README.md"
    },
    {
      "glob_source": "../LICENSE",
      "output": "LICENSE"
    }
  ]
}